eircode/__init__.py
eircode/address.py
eircode/constants.py
eircode/eircode.py
eircode/logging.py
eircode/proxy.py
eircode-0.0.46.dist-info/LICENSE
eircode-0.0.46.dist-info/METADATA
eircode-0.0.46.dist-info/WHEEL
eircode-0.0.46.dist-info/top_level.txt
eircode-0.0.46.dist-info/RECORD
